dephell_shells-0.1.5.dist-info/dependency_links.txt
dephell_shells-0.1.5.dist-info/entry_points.txt
dephell_shells-0.1.5.dist-info/METADATA
dephell_shells-0.1.5.dist-info/top_level.txt
dephell_shells-0.1.5.dist-info/WHEEL
dephell_shells/_manager.py
dephell_shells/_shells.py
dephell_shells/_base.py
dephell_shells/__init__.py
dephell_shells/__main__.py
dephell_shells/_utils.py
dephell_shells-0.1.5.dist-info/LICENSE
dephell_shells-0.1.5.dist-info/RECORD