Metadata-Version: 2.1
Name: dephell-shells
Version: 0.1.5
Summary: activate virtual environment for current shell
Project-URL: Repository, https://github.com/dephell/dephell_shells
Author: Gram
Author-email: gram@orsinium.dev
License: MIT
Requires-Python: >=3.6
Keywords: dephell,packaging,venv,pipenv,virtualenv
Classifier: Development Status :: 4 - Beta
Classifier: Environment :: Console
Classifier: Intended Audience :: Developers
Classifier: License :: OSI Approved :: MIT License
Classifier: Programming Language :: Python
Classifier: Topic :: Software Development :: Libraries :: Python Modules
Classifier: Topic :: System :: Installation/Setup
Classifier: Programming Language :: Python :: 3.5
Classifier: Programming Language :: Python :: 3.6
Classifier: Programming Language :: Python :: 3.7
Classifier: Programming Language :: Python :: 3.8
Classifier: Programming Language :: Python :: Implementation :: CPython
Classifier: Programming Language :: Python :: Implementation :: PyPy
Classifier: Operating System :: MacOS
Classifier: Operating System :: Microsoft :: Windows
Classifier: Operating System :: Unix
Requires-Dist: attrs
Requires-Dist: pexpect
Requires-Dist: shellingham
